MANIFEST.in
README-Pypi.md
README.md
setup.py
accessibility_toolbar/__init__.py
accessibility_toolbar.egg-info/PKG-INFO
accessibility_toolbar.egg-info/SOURCES.txt
accessibility_toolbar.egg-info/dependency_links.txt
accessibility_toolbar.egg-info/not-zip-safe
accessibility_toolbar.egg-info/requires.txt
accessibility_toolbar.egg-info/top_level.txt
accessibility_toolbar/static/main.js
accessibility_toolbar/static/font_style/color_control.js
accessibility_toolbar/static/font_style/font_control.js
accessibility_toolbar/static/font_style/font_spacing.js
accessibility_toolbar/static/font_style/font_style.css
accessibility_toolbar/static/font_style/font_style.js
accessibility_toolbar/static/font_style/predefined_styles.css
accessibility_toolbar/static/font_style/predefined_styles.js
accessibility_toolbar/static/font_style/spectrum.js
accessibility_toolbar/static/images/contrastmode.png
accessibility_toolbar/static/images/darkmode.png
accessibility_toolbar/static/images/notebook_styles.png
accessibility_toolbar/static/images/planner.png
accessibility_toolbar/static/images/spellchecker.png
accessibility_toolbar/static/images/styles.png
accessibility_toolbar/static/images/summary.gif
accessibility_toolbar/static/images/toolbar.png
accessibility_toolbar/static/images/voice.png
accessibility_toolbar/static/planner/planner.css
accessibility_toolbar/static/planner/planner.js
accessibility_toolbar/static/spell_checker/EN_dictionary.js
accessibility_toolbar/static/spell_checker/spc_function.js
accessibility_toolbar/static/spell_checker/spell_checker.js
accessibility_toolbar/static/spell_checker/spellchecker.css
accessibility_toolbar/static/themes/themes.css
accessibility_toolbar/static/themes/themes.js
accessibility_toolbar/static/voice_control/voice_control.css
accessibility_toolbar/static/voice_control/voice_control.js
jupyter-config/nbconfig/notebook.d/accessibility_toolbar.json