Metadata-Version: 2.1
Name: accessibility-toolbar
Version: 1.0.35
Summary: An Accessibility Toolbar for Jupyter Notebooks
Home-page: https://github.com/uclixnjupyternbaccessibility/accessibility_toolbar
Author: MSJUPYTER
Author-email: joshua.zeltser@gmail.com
License: UNKNOWN
Platform: UNKNOWN
Classifier: Programming Language :: Python :: 3
Classifier: License :: OSI Approved :: MIT License
Classifier: Operating System :: OS Independent
Requires-Python: >=3.6
